SchemaExtractor/__init__.py
SchemaExtractor/app.py
SchemaExtractor/cli.py
schemaextractor-1.0.2.dist-info/LICENSE.txt
schemaextractor-1.0.2.dist-info/METADATA
schemaextractor-1.0.2.dist-info/WHEEL
schemaextractor-1.0.2.dist-info/entry_points.txt
schemaextractor-1.0.2.dist-info/RECORD
