Metadata-Version: 2.1
Name: SchemaExtractor
Version: 1.0.2
Summary: SchemaExtractor: A Python library with a multi-agent architecture for extracting and analyzing schemas from knowledge graphs.
Home-page: https://github.com/sensein/SchemaExtractor
License: Apache-2.0
Keywords: python,package,template
Author: tekrajchhetri
Author-email: tekrajchhetri@gmail.com
Maintainer: tekrajchhetri
Maintainer-email: tekrajchhetri@gmail.com
Requires-Python: >=3.10,<4.0
Classifier: Development Status :: 3 - Alpha
Classifier: License :: OSI Approved :: Apache Software License
Classifier: Operating System :: OS Independent
Classifier: Programming Language :: Python :: 3
Classifier: Programming Language :: Python :: 3.10
Classifier: Programming Language :: Python :: 3.11
Classifier: Programming Language :: Python :: 3.12
Requires-Dist: click (>=8.1.7,<9.0.0)
Requires-Dist: pyautogen (>=0.2.0,<0.3.0)
Requires-Dist: rdflib (>=7.0.0,<8.0.0)
Project-URL: Documentation, https://tekrajchhetri.github.io/SchemaExtractor
Project-URL: Repository, https://github.com/sensein/SchemaExtractor
